main.py
jam_todos_cli-0.6.3.dist-info/METADATA
jam_todos_cli-0.6.3.dist-info/WHEEL
jam_todos_cli-0.6.3.dist-info/entry_points.txt
jam_todos_cli-0.6.3.dist-info/top_level.txt
jam_todos_cli-0.6.3.dist-info/RECORD
