Metadata-Version: 2.4
Name: jam-todos-cli
Version: 0.6.3
Summary: A simple and colorful To-Do List CLI
Author-email: JamilaYDhedhi <nurjamila1@gmail.com>
Requires-Python: >=3.11
Requires-Dist: rich>=14.0.0
Requires-Dist: toml>=0.10.2
Requires-Dist: typer>=0.15.2
